{"jTKozM+GEvRywRwHGWUTQA==":"1d4cca8dae3c0d6c8c96218502749f79-1000x582.jpeg","oRykAiO0rUD++7AmPeEwUg==":"background1.jpg","6MWK6K1cDjyCiLKmCkYnIg==":"654-886x1253.jpeg","YiydsNm/EwbUYkGfrHVXkA==":"1612474366_21-p-svetlo-serii-fon-abstraktsiya-22-1280x900.jpg","TZ0ITAgC9coA+E3OpHXuvA==":"1612474366_21-p-svetlo-serii-fon-abstraktsiya-22-1280x900.jpeg","C7BPhQor8jGPjozdZWS8jw==":"%D0%B1%D0%BE%D0%B1%D0%B8%D0%BA%20%D0%B2%20%D0%B3%D0%BE%D1%81%D1%82%D1%8F%D0%BA%20%D1%83%20%D0%B1%D0%B0%D1%80%D0%B1%D0%BE%D1%81%D0%B0-425x557.jpg","4HDVZXjPkdoLl/Nc+LrNog==":"1d4cca8dae3c0d6c8c96218502749f79-1000x582.jpg","cr48SywJiKh1mrhZsma01w==":"dtukhtavqaaabaz-1200x737.jpg","nBCU7RzzBWl0K2OL8O3bxw==":"1625556225_3-kartinkin-com-p-fon-kosmos-raketa-krasivie-foni-3-1600x900.jpg","N5r8WnCpC4A+Ga1izHuWmg==":"1625556225_3-kartinkin-com-p-fon-kosmos-raketa-krasivie-foni-3-1600x900.jpeg","oR3rWAOzVImrUmZEviXzQg==":"1625514046_35-kartinkin-com-p-fon-kosmos-zemlya-krasivie-foni-35-1600x898.jpg","Jj5r6TpAb/j39sW8BGWAQg==":"1611343970_52-p-kosmicheskii-fon-dlya-teksta-58-2000x1122.jpg","F7eK6b2KE6j8nJc9UHgW9g==":"41777500-639x800.jpg","Wiqzi2MtJZ2tUBBjIfx/4g==":"41777500-639x800.jpeg","3/lE7zjaMnG4xi9C9miPNA==":"3214-886x1253.jpeg","zPWdZiDLJyLHXKL+xgectw==":"7822946ryc-642x938.jpeg","OYavMg6o8NNgNaP6LiYLyQ==":"7822946ryc-1-642x938.jpeg","qOaDVcVeSyQBiq7c/nQMsA==":"7822946ryc-642x938.jpg","o8TGWUVcimELct181I1xhw==":"3214785-696x984.jpeg","GnL21zEAnNcN2dDKPpyrmA==":"3214785-1076x1522.jpeg","WARTY7Lwemvgd+xGj4sSZA==":"32147-696x984.jpeg","8u7zVEyEFq8Z07nmSQRm0w==":"126549-696x984.jpg","gGZZd6X54rnndho4W3NAgQ==":"1611343970_52-p-kosmicheskii-fon-dlya-teksta-58-1836x1030.jpg","3kSh5DzJIBIfN6hz7Ustjw==":"ivanovskiy-rakety-2005-554x801.jpg","sEmpC1rywr5grEoeM8c1Pw==":"-1-696x867.jpg","MNpT1Z83Jr1ZEO72YKdKOw==":"background1.jpeg","R6MqR7+7o+3pOjuimVc8ig==":"dtukhtavqaaabaz-1-1200x737.jpg","lXwGYs+wNuUsvEz3ZOHX1A==":"korolev-7-910x647.jpg","U5LdDo0/GlwxlR9z8ZLs8g==":"utg;ittitt-1000x641.jpg","0bflRCvVDNBjPvfVj8f6Pg==":"10c5443514e5a23246861b68f9b721a7-1900x1412.jpg","dprPQOq+RMfroxtkD3E0cg==":"img800_463fecc5eae02facd4c51ba3eab391ef-800x800.jpeg","CfDcQLBERikID3UBSirPvg==":"22390_beloglazova-696x689.jpg","CuR4NW+cuzm5fEKeqaH7yw==":"apenchenko-sergei-69-488x644.jpg","iT+44/8peNBZ/eYiq00AvA==":"a6e7c5ea8aa1b4e0c3befe8c0bbdf84c31fb3223-696x901.jpg","EAMgWeZfMv4sCihsFHJZng==":"apenchenko-sergei-69-488x644.jpeg","PDXx71oZcD88aChQmbYx8g==":"54344-300x490.jpg","3DjiLPMJRDCAB493CvTnYw==":"1618935972_25-phonoteka_org-p-neitralnii-fon-kosmos-30-1920x1080.jpg","0eQ53WdAJYjtfANrAopP6w==":"1614365951_42-p-svetlii-kosmicheskii-fon-60-1920x1200.jpg","r+CsInRYKaDRTOXHc43XJg==":"classic_1024x537-21038522-696x365.jpeg"}